docs/Makefile
docs/api_reference.rst
docs/conf.py
docs/contributing.rst
docs/history.rst
docs/index.rst
docs/make.bat
docs/pyrato.rst
docs/readme.rst
docs/modules/analytic.rst
docs/modules/pyrato.rst
pyrato/__init__.py
pyrato/dsp.py
pyrato/edc.py
pyrato/rap.py
pyrato/roomacoustics.py
pyrato/analytic/__init__.py
pyrato/analytic/analytic.py
pyrato/analytic/impedance.py
pyrato-0.4.1.dist-info/licenses/LICENSE
tests/__init__.py
tests/test_analytic.py
tests/test_analytic_impedance.py
tests/test_deprecation_warnings.py
tests/test_dsp.py
tests/test_edc.py
tests/test_edc_noise_handling.py
tests/test_roomacoustics.py
tests/test_rt.py
tests/data/analytic_rir_impedance.npy
tests/data/analytic_rir_impedance_no_cav.npy
tests/data/analytic_rir_rigid_walls.csv
tests/data/analytic_rtf_impedance.npy
tests/data/analytic_rtf_impedance_no_cav.npy
tests/data/analytic_impedance/k_ns_x.csv
tests/data/analytic_impedance/k_ns_x_zeta15.csv
tests/data/analytic_impedance/k_ns_y.csv
tests/data/analytic_impedance/k_ns_y_zeta15.csv
tests/data/analytic_impedance/k_ns_z.csv
tests/data/analytic_impedance/k_ns_z_zeta15.csv
tests/data/analytic_impedance/ks.csv
tests/data/analytic_impedance/mode_indices.csv
tests/data/analytic_impedance/mode_indices_zeta15.csv
tests/data/analytic_impedance/p_x.csv
tests/data/analytic_impedance/p_x_zeta15.csv
tests/private/comparison_fenics.ipynb
tests/private/rectangular_room_impedance.ipynb
tests/private/fenics/ks_fenics.csv
tests/private/fenics/p_R_fenics.csv
tests/test_data/analytic_rir_psnr50_1D.csv
tests/test_data/analytic_rir_psnr50_2D.csv
tests/test_data/edc_chu_1D.csv
tests/test_data/edc_chu_2D.csv
tests/test_data/edc_lundeby_1D.csv
tests/test_data/edc_lundeby_2D.csv
tests/test_data/edc_lundeby_chu_1D.csv
tests/test_data/edc_lundeby_chu_2D.csv
tests/test_data/edc_truncation_1D.csv
tests/test_data/edc_truncation_2D.csv
tests/test_data/generate_test_data.py
tests/test_data/intersection_time_1D.csv
tests/test_data/intersection_time_2D.csv
tests/test_data/noise_energy_1D.csv
pyrato-0.4.1.dist-info/METADATA
pyrato-0.4.1.dist-info/WHEEL
pyrato-0.4.1.dist-info/top_level.txt
pyrato-0.4.1.dist-info/RECORD
