Metadata-Version: 2.4
Name: pyrato
Version: 0.4.1
Summary: Collection of functions commonly used in room acoustics.
Author-email: The pyfar developers <info@pyfar.org>
License: MIT License
Project-URL: Tracker, https://github.com/pyfar/pyrato/issues
Project-URL: Documentation, https://pyrato.readthedocs.io/
Project-URL: Download, https://pypi.org/project/pyrato/
Project-URL: Homepage, https://pyfar.org/
Project-URL: Source, https://github.com/pyfar/pyrato
Project-URL: Changelog, https://github.com/pyfar/pyrato/blob/main/HISTORY.rst
Keywords: acoustics,pyfar
Classifier: Development Status :: 4 - Beta
Classifier: Intended Audience :: Science/Research
Classifier: License :: OSI Approved :: MIT License
Classifier: Natural Language :: English
Classifier: Programming Language :: Python :: 3
Classifier: Programming Language :: Python :: 3.9
Classifier: Programming Language :: Python :: 3.10
Classifier: Programming Language :: Python :: 3.11
Classifier: Programming Language :: Python :: 3.12
Classifier: Programming Language :: Python :: 3.13
Requires-Python: >=3.9
License-File: LICENSE
Requires-Dist: pyfar>=0.5.0
Requires-Dist: numpy>=1.14.0
Requires-Dist: scipy>=1.5.0
Requires-Dist: matplotlib
Provides-Extra: deploy
Requires-Dist: twine; extra == "deploy"
Requires-Dist: wheel; extra == "deploy"
Requires-Dist: build; extra == "deploy"
Requires-Dist: setuptools; extra == "deploy"
Requires-Dist: bump-my-version; extra == "deploy"
Provides-Extra: tests
Requires-Dist: pytest; extra == "tests"
Requires-Dist: pytest-cov; extra == "tests"
Requires-Dist: watchdog; extra == "tests"
Requires-Dist: ruff==0.8.3; extra == "tests"
Requires-Dist: coverage; extra == "tests"
Provides-Extra: docs
Requires-Dist: sphinx; extra == "docs"
Requires-Dist: autodocsumm>=0.2.14; extra == "docs"
Requires-Dist: pydata-sphinx-theme; extra == "docs"
Requires-Dist: sphinx_mdinclude; extra == "docs"
Requires-Dist: sphinx-design; extra == "docs"
Requires-Dist: sphinx-favicon; extra == "docs"
Requires-Dist: sphinx-reredirects; extra == "docs"
Provides-Extra: dev
Requires-Dist: pyrato[deploy,docs,tests]; extra == "dev"
Dynamic: license-file
